{
	"name": "Excavated Evil",
	"description": "Deal 3 damage to all minions. Shuffle this card into your opponent's deck.",
	"id": "spell_excavated_evil",
	"type": "SPELL",
	"rarity": "RARE",
	"heroClass": "PRIEST",
	"baseManaCost": 5,
	"collectible": true,
	"targetSelection": "NONE",
	"spell": {
		"class": "MetaSpell",
		"spell1": {
			"class": "DamageSpell",
			"value": 3,
			"target": "ALL_MINIONS"
		},
		"spell2": {
			"class": "ShuffleToDeckSpell",
			"card": "spell_excavated_evil",
			"targetPlayer": "OPPONENT"
		}
	},
	"set": "LEAGUE_OF_EXPLORERS",
	"fileFormatVersion": 1
}
