{
	"id": "secret_competitive_spirit",
	"name": "Competitive Spirit",
	"baseManaCost": 1,
	"type": "SPELL",
	"heroClass": "PALADIN",
	"rarity": "RARE",
	"description": "Secret: When your turn starts, give your minions +1/+1.",
	"targetSelection": "NONE",
	"trigger": {
		"class": "TurnEndTrigger",
		"targetPlayer": "OPPONENT",
		"fireCondition": {
			"class": "MinionCountCondition",
			"value": 0,
			"operation": "GREATER"
		}
	},
	"spell": {
		"class": "BuffSpell",
		"target": "FRIENDLY_MINIONS",
		"attackBonus": 1,
		"hpBonus": 1
	},
	"collectible": true,
	"set": "THE_GRAND_TOURNAMENT",
	"fileFormatVersion": 1
}